macrometa_source_oracle/__init__.py
macrometa_source_oracle/connection.py
macrometa_source_oracle/sync_strategies/__init__.py
macrometa_source_oracle/sync_strategies/common.py
macrometa_source_oracle/sync_strategies/full_table.py
macrometa_source_oracle/sync_strategies/log_based.py
macrometa_source_oracle-1.0.0.dist-info/entry_points.txt
macrometa_source_oracle-1.0.0.dist-info/LICENSE
macrometa_source_oracle-1.0.0.dist-info/WHEEL
macrometa_source_oracle-1.0.0.dist-info/METADATA
macrometa_source_oracle-1.0.0.dist-info/RECORD
