Metadata-Version: 2.1
Name: macrometa-source-oracle
Version: 1.0.0
Summary: Macrometa source oracle connector for reading from oracle databases.
Home-page: https://www.macrometa.com/
License: Apache-2.0
Keywords: ELT,Connectors,Workflows,Macrometa,Oracle,Source
Author: Macrometa
Author-email: info@macrometa.com
Requires-Python: >=3.8.1,<3.11
Classifier: License :: OSI Approved :: Apache Software License
Classifier: Operating System :: OS Independent
Classifier: Programming Language :: Python :: 3
Classifier: Programming Language :: Python :: 3.9
Classifier: Programming Language :: Python :: 3.10
Classifier: Programming Language :: Python :: 3
Classifier: Programming Language :: Python :: 3.8
Requires-Dist: c8connector (>=0.0.24)
Requires-Dist: oracledb (>=1.2.2,<2.0.0)
Requires-Dist: pipelinewise-singer-python (==1.2.0)
Requires-Dist: prometheus-client (==0.16.0)
Requires-Dist: strict-rfc3339 (>=0.7,<0.8)
Project-URL: Bug Tracker, https://github.com/Macrometacorp/macrometa-source-oracle/issues
